Assignment-Under the Hood/Assignment 1 Q3/fsm.v



// I am getting delayed results, the output/state is one step behind the current temperature



`timescale 1ms/1ms
module fsm(input [4:0] temp, input clk, output reg [1:0]out, s);

    reg [1:0] state, next_state;

    initial begin
        state = 2'b00;
        next_state = 2'b00;
        out = 2'b00;
    end

    always @(posedge clk) begin
        if (state == 2'b00) begin
            if(temp < 12)begin
                next_state = 2'b10;
            end else if(temp > 18)begin
                next_state = 2'b01;
            end else begin
                next_state = state;
            end
        end else if(state == 2'b10) begin
            if(temp > 26) begin
                next_state = 2'b01;
            end else if(temp > 20)begin
                next_state = 2'b00;
            end else begin
                next_state = state;
            end
        end else begin
            if(temp < 8) begin
                next_state = 2'b10;
            end else if(temp < 14) begin
                next_state = 2'b00;
            end else begin
                next_state = state;
            end
        end
    end

    always @(negedge clk) begin
        out = next_state;
    end

    always @(negedge clk) begin
        state = next_state;
        s = next_state;
    end

endmodule


module tb;

    reg clk;
    reg [4:0] temp;
    wire [1:0] o, s;

    fsm f(temp, clk, o, s);

    always begin
        #5;
        clk = ~clk;
    end

    always @(posedge clk) begin
        $display("temp = %d, o = %b, s = %b", temp, o, s);
    end

    initial begin
        clk = 0;
        temp = 0;

        $dumpfile("fsm.vcd");
        $dumpvars(0, tb);
        
        #10;
        repeat(10) begin
            temp = $random;
            #10;
        end
        
        temp = 21;
        #10;
        temp = 11;
        #10;
        temp = 28;
        #10;
        temp = 15;
        #10;
        $finish;
    end
    
endmodule

Assignment-Under the Hood/Assignment 1 Q3/fsm.vcd
$date
	Wed Jun 22 02:13:24 2022
$end
$version
	Icarus Verilog
$end
$timescale
	1ms
$end
$scope module tb $end
$var wire 2 ! s [1:0] $end
$var wire 2 " o [1:0] $end
$var reg 1 # clk $end
$var reg 5 $ temp [4:0] $end
$scope module f $end
$var wire 1 # clk $end
$var wire 5 % temp [4:0] $end
$var reg 2 & next_state [1:0] $end
$var reg 2 ' out [1:0] $end
$var reg 2 ( s [1:0] $end
$var reg 2 ) state [1:0] $end
$upscope $end
$upscope $end
$enddefinitions $end
#0
$dumpvars
b0 )
b0 (
b0 '
b0 &
b0 %
b0 $
0#
b0 "
b0 !
$end
#5
b10 &
1#
#10
b10 !
b10 (
b10 )
b10 "
b10 '
0#
b100 $
b100 %
#15
1#
#20
0#
b1 $
b1 %
#25
1#
#30
0#
b1001 $
b1001 %
#35
1#
#40
0#
b11 $
b11 %
#45
1#
#50
0#
b1101 $
b1101 %
#55
1#
#60
0#
#65
1#
#70
0#
b101 $
b101 %
#75
1#
#80
0#
b10010 $
b10010 %
#85
1#
#90
0#
b1 $
b1 %
#95
1#
#100
0#
b1101 $
b1101 %
#105
1#
#110
0#
b10101 $
b10101 %
#115
b0 &
1#
#120
b0 "
b0 '
b0 !
b0 (
b0 )
0#
b1011 $
b1011 %
#125
b10 &
1#
#130
b10 !
b10 (
b10 )
b10 "
b10 '
0#
b11100 $
b11100 %
#135
b1 &
1#
#140
b1 "
b1 '
b1 !
b1 (
b1 )
0#
b1111 $
b1111 %
